STIC_JPL/ECOv002-cal-val-STIC-JPL-inputs.csv
STIC_JPL/ECOv002-cal-val-STIC-JPL-outputs.csv
STIC_JPL/ECOv002_calval_STIC_inputs.py
STIC_JPL/FVC_from_NDVI.py
STIC_JPL/LAI_from_NDVI.py
STIC_JPL/STIC_JPL.py
STIC_JPL/__init__.py
STIC_JPL/canopy_air_stream.py
STIC_JPL/celcius_to_kelvin.py
STIC_JPL/closure.py
STIC_JPL/constants.py
STIC_JPL/exceptions.py
STIC_JPL/generate_STIC_inputs.py
STIC_JPL/initialize_with_solar.py
STIC_JPL/initialize_without_solar.py
STIC_JPL/iterate_with_solar.py
STIC_JPL/iterate_without_solar.py
STIC_JPL/model.py
STIC_JPL/net_radiation.py
STIC_JPL/process_STIC_table.py
STIC_JPL/root_zone_initialization.py
STIC_JPL/root_zone_iteration.py
STIC_JPL/soil_moisture_initialization.py
STIC_JPL/soil_moisture_iteration.py
STIC_JPL/verify.py
STIC_JPL/version.py
tests/test_import_STIC.py
tests/test_import_dependencies.py
tests/test_verify.py
stic_jpl-1.6.0.dist-info/METADATA
stic_jpl-1.6.0.dist-info/WHEEL
stic_jpl-1.6.0.dist-info/top_level.txt
stic_jpl-1.6.0.dist-info/RECORD
