Metadata-Version: 2.4
Name: STIC-JPL
Version: 1.6.0
Summary: Surface Temperature Initiated Closure (STIC) Evapotranspiration Model Python Implementation
Author-email: Gregory Halverson <gregory.h.halverson@jpl.nasa.gov>, Kaniska Mallick <kaniska.mallick@list.lu>, Madeleine Pascolini-Campbell <madeleine.a.pascolini-campbell@jpl.nasa.gov>, "Claire S. Villanueva-Weeks" <claire.s.villanueva-weeks@jpl.gov>
Project-URL: Homepage, https://github.com/JPL-Evapotranspiration-Algorithms/STIC-JPL
Classifier: Programming Language :: Python :: 3
Classifier: Operating System :: OS Independent
Requires-Python: >=3.10
Requires-Dist: BESS-JPL>=1.21.0
Requires-Dist: check-distribution
Requires-Dist: colored-logging
Requires-Dist: daylight-evapotranspiration>=1.3.4
Requires-Dist: ECOv002-calval-tables>=1.11.0
Requires-Dist: ECOv002-CMR>=1.0.5
Requires-Dist: ECOv002-granules>=1.0.3
Requires-Dist: ECOv003-granules
Requires-Dist: GEOS5FP>=1.1.1
Requires-Dist: monte-carlo-sensitivity
Requires-Dist: numpy
Requires-Dist: pandas
Requires-Dist: pytictoc
Requires-Dist: rasters>=1.4.6
Requires-Dist: seaborn
Requires-Dist: SEBAL-soil-heat-flux
Requires-Dist: solar-apparent-time>=1.5.3
Requires-Dist: verma-net-radiation>=1.1.0
Provides-Extra: dev
Requires-Dist: build; extra == "dev"
Requires-Dist: pytest>=6.0; extra == "dev"
Requires-Dist: pytest-cov; extra == "dev"
Requires-Dist: jupyter; extra == "dev"
Requires-Dist: pytest; extra == "dev"
Requires-Dist: twine; extra == "dev"
